{
  "id": "natrinai_127",
  "poem": "natrinai",
  "tinai": "neytal",
  "sangamTamil": "இருங் கழி துழைஇய ஈர்ம் புற நாரை\nஇற எறி திவலையின் பனிக்கும் பாக்கத்து,\nஉவன் வரின், எவனோ?- பாண!- பேதை\nகொழு மீன் ஆர்கைச் செழு நகர் நிறைந்த\nகல்லாக் கதவர் தன் ஐயர் ஆகவும்,\nவண்டல் ஆயமொடு பண்டு தான் ஆடிய\nஈனாப் பாவை தலையிட்டு ஓரும்,\n'மெல்லம் புலம்பன் அன்றியும்,\nசெல்வாம்' என்னும், 'கானலானே'.\n- சீத்தலைச் சாத்தனார்.",
  "urai": "பாணனே! எம் பேதையானவள் கொழுவிய மீனை யுண்ணுதலையுடைய செழுமையுற்ற மாளிகையில் நிறைந்த தன் ஐயன்மார் தமது தொழிலன்றி ஏனைய ஒன்றுங் கல்லாத சினமுடையராயிருப்பவும்; பண்டு தோழியரோடு தான் வண்டல் விளையாட்டு அயர்தற்குத் தான் ஈனாது வைத்த பாவை தலைக்கீடாகக் கொண்டு; அந்த மெல்லிய கடற்கரைச் சேர்ப்பனை அல்லாமலும் கழிக்கரைச் சோலையின்கண் விளையாடச் செல்வோமாக என்று கூறாநிற்பாள்; அதனால் கரிய கழியிலே இரை தேடித் துழாவிய ஈரிய புறத்தையுடைய நாரை தன் சிறகை உதறுகின்ற திவலையாலே குளிர்ந்து நடுங்குகின்ற நமது பாக்கத்தில்; அந்த மெல்லம்புலம்பன் வருதலால் யாது பயனோ? ஆதலின் அவன் இனி வரற்பாலன் அல்லன்காண்!",
  "english": null,
  "lines": [
    {
      "lineNumber": 1,
      "text": "இருங் கழி துழைஇய ஈர்ம் புற நாரை",
      "words": [
        {
          "form": "இருங்",
          "root": null,
          "urichol": null,
          "etymology": null,
          "gloss": null
        },
        {
          "form": "கழி",
          "root": null,
          "urichol": null,
          "etymology": null,
          "gloss": null
        },
        {
          "form": "துழைஇய",
          "root": null,
          "urichol": null,
          "etymology": null,
          "gloss": null
        },
        {
          "form": "ஈர்ம்",
          "root": null,
          "urichol": null,
          "etymology": null,
          "gloss": null
        },
        {
          "form": "புற",
          "root": null,
          "urichol": null,
          "etymology": null,
          "gloss": null
        },
        {
          "form": "நாரை",
          "root": null,
          "urichol": null,
          "etymology": null,
          "gloss": null
        }
      ]
    },
    {
      "lineNumber": 2,
      "text": "இற எறி திவலையின் பனிக்கும் பாக்கத்து,",
      "words": [
        {
          "form": "இற",
          "root": null,
          "urichol": null,
          "etymology": null,
          "gloss": null
        },
        {
          "form": "எறி",
          "root": null,
          "urichol": null,
          "etymology": null,
          "gloss": null
        },
        {
          "form": "திவலையின்",
          "root": null,
          "urichol": null,
          "etymology": null,
          "gloss": null
        },
        {
          "form": "பனிக்கும்",
          "root": null,
          "urichol": null,
          "etymology": null,
          "gloss": null
        },
        {
          "form": "பாக்கத்து,",
          "root": null,
          "urichol": null,
          "etymology": null,
          "gloss": null
        }
      ]
    },
    {
      "lineNumber": 3,
      "text": "உவன் வரின், எவனோ?- பாண!- பேதை",
      "words": [
        {
          "form": "உவன்",
          "root": null,
          "urichol": null,
          "etymology": null,
          "gloss": null
        },
        {
          "form": "வரின்,",
          "root": null,
          "urichol": null,
          "etymology": null,
          "gloss": null
        },
        {
          "form": "எவனோ?-",
          "root": null,
          "urichol": null,
          "etymology": null,
          "gloss": null
        },
        {
          "form": "பாண!-",
          "root": null,
          "urichol": null,
          "etymology": null,
          "gloss": null
        },
        {
          "form": "பேதை",
          "root": null,
          "urichol": null,
          "etymology": null,
          "gloss": null
        }
      ]
    },
    {
      "lineNumber": 4,
      "text": "கொழு மீன் ஆர்கைச் செழு நகர் நிறைந்த",
      "words": [
        {
          "form": "கொழு",
          "root": null,
          "urichol": null,
          "etymology": null,
          "gloss": null
        },
        {
          "form": "மீன்",
          "root": null,
          "urichol": null,
          "etymology": null,
          "gloss": null
        },
        {
          "form": "ஆர்கைச்",
          "root": null,
          "urichol": null,
          "etymology": null,
          "gloss": null
        },
        {
          "form": "செழு",
          "root": null,
          "urichol": null,
          "etymology": null,
          "gloss": null
        },
        {
          "form": "நகர்",
          "root": null,
          "urichol": null,
          "etymology": null,
          "gloss": null
        },
        {
          "form": "நிறைந்த",
          "root": null,
          "urichol": null,
          "etymology": null,
          "gloss": null
        }
      ]
    },
    {
      "lineNumber": 5,
      "text": "கல்லாக் கதவர் தன் ஐயர் ஆகவும்,",
      "words": [
        {
          "form": "கல்லாக்",
          "root": null,
          "urichol": null,
          "etymology": null,
          "gloss": null
        },
        {
          "form": "கதவர்",
          "root": null,
          "urichol": null,
          "etymology": null,
          "gloss": null
        },
        {
          "form": "தன்",
          "root": null,
          "urichol": null,
          "etymology": null,
          "gloss": null
        },
        {
          "form": "ஐயர்",
          "root": null,
          "urichol": null,
          "etymology": null,
          "gloss": null
        },
        {
          "form": "ஆகவும்,",
          "root": null,
          "urichol": null,
          "etymology": null,
          "gloss": null
        }
      ]
    },
    {
      "lineNumber": 6,
      "text": "வண்டல் ஆயமொடு பண்டு தான் ஆடிய",
      "words": [
        {
          "form": "வண்டல்",
          "root": null,
          "urichol": null,
          "etymology": null,
          "gloss": null
        },
        {
          "form": "ஆயமொடு",
          "root": null,
          "urichol": null,
          "etymology": null,
          "gloss": null
        },
        {
          "form": "பண்டு",
          "root": null,
          "urichol": null,
          "etymology": null,
          "gloss": null
        },
        {
          "form": "தான்",
          "root": null,
          "urichol": null,
          "etymology": null,
          "gloss": null
        },
        {
          "form": "ஆடிய",
          "root": null,
          "urichol": null,
          "etymology": null,
          "gloss": null
        }
      ]
    },
    {
      "lineNumber": 7,
      "text": "ஈனாப் பாவை தலையிட்டு ஓரும்,",
      "words": [
        {
          "form": "ஈனாப்",
          "root": null,
          "urichol": null,
          "etymology": null,
          "gloss": null
        },
        {
          "form": "பாவை",
          "root": null,
          "urichol": null,
          "etymology": null,
          "gloss": null
        },
        {
          "form": "தலையிட்டு",
          "root": null,
          "urichol": null,
          "etymology": null,
          "gloss": null
        },
        {
          "form": "ஓரும்,",
          "root": null,
          "urichol": null,
          "etymology": null,
          "gloss": null
        }
      ]
    },
    {
      "lineNumber": 8,
      "text": "'மெல்லம் புலம்பன் அன்றியும்,",
      "words": [
        {
          "form": "'மெல்லம்",
          "root": null,
          "urichol": null,
          "etymology": null,
          "gloss": null
        },
        {
          "form": "புலம்பன்",
          "root": null,
          "urichol": null,
          "etymology": null,
          "gloss": null
        },
        {
          "form": "அன்றியும்,",
          "root": null,
          "urichol": null,
          "etymology": null,
          "gloss": null
        }
      ]
    },
    {
      "lineNumber": 9,
      "text": "செல்வாம்' என்னும், 'கானலானே'.",
      "words": [
        {
          "form": "செல்வாம்'",
          "root": null,
          "urichol": null,
          "etymology": null,
          "gloss": null
        },
        {
          "form": "என்னும்,",
          "root": null,
          "urichol": null,
          "etymology": null,
          "gloss": null
        },
        {
          "form": "'கானலானே'.",
          "root": null,
          "urichol": null,
          "etymology": null,
          "gloss": null
        }
      ]
    },
    {
      "lineNumber": 10,
      "text": "- சீத்தலைச் சாத்தனார்.",
      "words": [
        {
          "form": "-",
          "root": null,
          "urichol": null,
          "etymology": null,
          "gloss": null
        },
        {
          "form": "சீத்தலைச்",
          "root": null,
          "urichol": null,
          "etymology": null,
          "gloss": null
        },
        {
          "form": "சாத்தனார்.",
          "root": null,
          "urichol": null,
          "etymology": null,
          "gloss": null
        }
      ]
    }
  ],
  "culturalNotes": [],
  "audioUrl": null,
  "source": "http://www.sangathamizh.com/8thokai/natrinai/natrinai-நற்றிணை127.html",
  "verified": false,
  "number": 127,
  "poet": "சீத்தலைச் சாத்தனார்."
}