{
  "id": "natrinai_234",
  "poem": "natrinai",
  "tinai": "kurinji",
  "sangamTamil": "சான்றோர் வருந்திய வருத்தமும் நுமது\nவான் தோய்வு அன்ன குடிமையும் நோக்கித்\nதிரு மணி வரன்றும் குன்றம் கொண்டு இவள்\nவரு முலை ஆகம் வழங்கினோ நன்றே அஃது ஆன்று\nஅடை பொருள் கருதுவிர் ஆயின் குடையொடு\nகழுமலம் தந்த நல் தேர்ச் செம்பியன்\nபங்குனி விழவின் உறந்தையொடு\nஉள்ளி விழவின் வஞ்சியும் சிறிதே.\n- ஆசிரியர் அறியப்படவில்லை.",
  "urai": "நமரங்காள்! நம்பால் மகட்பேசும் பொருட்டு அருங்கலம் முதலியன சுமந்து நம்மில்லிற்கு வந்துள்ள இப் பெரியோருடைய வழிநடை வருத்தத்தையும்; நுங்களுடைய வானைத் தீண்டுமளவு உயர்ந்தாற் போன்றுயர்ந்து திகழும் குலச்சிறப்பினையும் நினைந்துபார்த்து; நம்மகளின் மார்பின்கண் கணந்தொறும் வளராநின்ற முலைக்கு விலையாக; இச் சான்றோராற் குறிப்பிடப்படுகின்ற அருவிநீர் அழகிய மணிகளை வரன்றி வீழ்தற்கிடனான தலைவனது குன்றத்தையே ஏற்றுக்கொண்டு; இவளை அந் நம்பிக்கே வழங்கின் பெரிதும், நன்று நன்றாகும்; அங்ஙனமின்றி; நம் மகளின் முலைக்கு விலையாக அவர் தரும் பொருளைச் சீர்தூக்கு வீராயின்; கழுமலப் போரின்கண் மாற்றாரை அவர்தங் குடையோடே அகப்படுத்திய வெற்றியையுடைய நல்ல தேரினையுடைய சோழன் தலைநகராகிய; பங்குனித்திங்களிலே விழாவெடுக்கும் உறந்தையோடே கூடிய; உள்ளி விழா நிகழ்தற்கிடனான சேரன் தலைநகராகிய வஞ்சிதானும் ஈடில்லாச் சிறிதாய்விடுங் கண்டீர் : ஆதலால் இச் சான்றோர் தரும் பொருளை ஏற்று இவளை அந் நம்பிக்கே ஈதல் நன்று; என்பதாம்.",
  "english": null,
  "lines": [
    {
      "lineNumber": 1,
      "text": "சான்றோர் வருந்திய வருத்தமும் நுமது",
      "words": [
        {
          "form": "சான்றோர்",
          "root": null,
          "urichol": null,
          "etymology": null,
          "gloss": null
        },
        {
          "form": "வருந்திய",
          "root": null,
          "urichol": null,
          "etymology": null,
          "gloss": null
        },
        {
          "form": "வருத்தமும்",
          "root": null,
          "urichol": null,
          "etymology": null,
          "gloss": null
        },
        {
          "form": "நுமது",
          "root": null,
          "urichol": null,
          "etymology": null,
          "gloss": null
        }
      ]
    },
    {
      "lineNumber": 2,
      "text": "வான் தோய்வு அன்ன குடிமையும் நோக்கித்",
      "words": [
        {
          "form": "வான்",
          "root": null,
          "urichol": null,
          "etymology": null,
          "gloss": null
        },
        {
          "form": "தோய்வு",
          "root": null,
          "urichol": null,
          "etymology": null,
          "gloss": null
        },
        {
          "form": "அன்ன",
          "root": null,
          "urichol": null,
          "etymology": null,
          "gloss": null
        },
        {
          "form": "குடிமையும்",
          "root": null,
          "urichol": null,
          "etymology": null,
          "gloss": null
        },
        {
          "form": "நோக்கித்",
          "root": null,
          "urichol": null,
          "etymology": null,
          "gloss": null
        }
      ]
    },
    {
      "lineNumber": 3,
      "text": "திரு மணி வரன்றும் குன்றம் கொண்டு இவள்",
      "words": [
        {
          "form": "திரு",
          "root": null,
          "urichol": null,
          "etymology": null,
          "gloss": null
        },
        {
          "form": "மணி",
          "root": null,
          "urichol": null,
          "etymology": null,
          "gloss": null
        },
        {
          "form": "வரன்றும்",
          "root": null,
          "urichol": null,
          "etymology": null,
          "gloss": null
        },
        {
          "form": "குன்றம்",
          "root": null,
          "urichol": null,
          "etymology": null,
          "gloss": null
        },
        {
          "form": "கொண்டு",
          "root": null,
          "urichol": null,
          "etymology": null,
          "gloss": null
        },
        {
          "form": "இவள்",
          "root": null,
          "urichol": null,
          "etymology": null,
          "gloss": null
        }
      ]
    },
    {
      "lineNumber": 4,
      "text": "வரு முலை ஆகம் வழங்கினோ நன்றே அஃது ஆன்று",
      "words": [
        {
          "form": "வரு",
          "root": null,
          "urichol": null,
          "etymology": null,
          "gloss": null
        },
        {
          "form": "முலை",
          "root": null,
          "urichol": null,
          "etymology": null,
          "gloss": null
        },
        {
          "form": "ஆகம்",
          "root": null,
          "urichol": null,
          "etymology": null,
          "gloss": null
        },
        {
          "form": "வழங்கினோ",
          "root": null,
          "urichol": null,
          "etymology": null,
          "gloss": null
        },
        {
          "form": "நன்றே",
          "root": null,
          "urichol": null,
          "etymology": null,
          "gloss": null
        },
        {
          "form": "அஃது",
          "root": null,
          "urichol": null,
          "etymology": null,
          "gloss": null
        },
        {
          "form": "ஆன்று",
          "root": null,
          "urichol": null,
          "etymology": null,
          "gloss": null
        }
      ]
    },
    {
      "lineNumber": 5,
      "text": "அடை பொருள் கருதுவிர் ஆயின் குடையொடு",
      "words": [
        {
          "form": "அடை",
          "root": null,
          "urichol": null,
          "etymology": null,
          "gloss": null
        },
        {
          "form": "பொருள்",
          "root": null,
          "urichol": null,
          "etymology": null,
          "gloss": null
        },
        {
          "form": "கருதுவிர்",
          "root": null,
          "urichol": null,
          "etymology": null,
          "gloss": null
        },
        {
          "form": "ஆயின்",
          "root": null,
          "urichol": null,
          "etymology": null,
          "gloss": null
        },
        {
          "form": "குடையொடு",
          "root": null,
          "urichol": null,
          "etymology": null,
          "gloss": null
        }
      ]
    },
    {
      "lineNumber": 6,
      "text": "கழுமலம் தந்த நல் தேர்ச் செம்பியன்",
      "words": [
        {
          "form": "கழுமலம்",
          "root": null,
          "urichol": null,
          "etymology": null,
          "gloss": null
        },
        {
          "form": "தந்த",
          "root": null,
          "urichol": null,
          "etymology": null,
          "gloss": null
        },
        {
          "form": "நல்",
          "root": null,
          "urichol": null,
          "etymology": null,
          "gloss": null
        },
        {
          "form": "தேர்ச்",
          "root": null,
          "urichol": null,
          "etymology": null,
          "gloss": null
        },
        {
          "form": "செம்பியன்",
          "root": null,
          "urichol": null,
          "etymology": null,
          "gloss": null
        }
      ]
    },
    {
      "lineNumber": 7,
      "text": "பங்குனி விழவின் உறந்தையொடு",
      "words": [
        {
          "form": "பங்குனி",
          "root": null,
          "urichol": null,
          "etymology": null,
          "gloss": null
        },
        {
          "form": "விழவின்",
          "root": null,
          "urichol": null,
          "etymology": null,
          "gloss": null
        },
        {
          "form": "உறந்தையொடு",
          "root": null,
          "urichol": null,
          "etymology": null,
          "gloss": null
        }
      ]
    },
    {
      "lineNumber": 8,
      "text": "உள்ளி விழவின் வஞ்சியும் சிறிதே.",
      "words": [
        {
          "form": "உள்ளி",
          "root": null,
          "urichol": null,
          "etymology": null,
          "gloss": null
        },
        {
          "form": "விழவின்",
          "root": null,
          "urichol": null,
          "etymology": null,
          "gloss": null
        },
        {
          "form": "வஞ்சியும்",
          "root": null,
          "urichol": null,
          "etymology": null,
          "gloss": null
        },
        {
          "form": "சிறிதே.",
          "root": null,
          "urichol": null,
          "etymology": null,
          "gloss": null
        }
      ]
    },
    {
      "lineNumber": 9,
      "text": "- ஆசிரியர் அறியப்படவில்லை.",
      "words": [
        {
          "form": "-",
          "root": null,
          "urichol": null,
          "etymology": null,
          "gloss": null
        },
        {
          "form": "ஆசிரியர்",
          "root": null,
          "urichol": null,
          "etymology": null,
          "gloss": null
        },
        {
          "form": "அறியப்படவில்லை.",
          "root": null,
          "urichol": null,
          "etymology": null,
          "gloss": null
        }
      ]
    }
  ],
  "culturalNotes": [],
  "audioUrl": null,
  "source": "http://www.sangathamizh.com/8thokai/natrinai/natrinai-நற்றிணை234.html",
  "verified": false,
  "number": 234,
  "poet": "ஆசிரியர் அறியப்படவில்லை."
}