{
  "id": "kurunthokai_175",
  "poem": "kurunthokai",
  "tinai": "neytal",
  "sangamTamil": "பருவத் தேன் நசைஇப் பல் பறைத் தொழுதி,\nஉரவுத் திரை பொருத திணிமணல் அடைகரை,\nநனைந்த புன்னை மாச் சினை தொகூஉம்\nமலர்ந்த பூவின் மா நீர்ச் சேர்ப்பற்கு\nஇரங்கேன் - தோழி! - 'ஈங்கு என் கொல்?' என்று\nபிறர்பிறர் அறியக் கூறல்\nஅமைந்தாங்கு அமைக; அம்பல் அஃது எவனே?\n- உலோச்சனார்.",
  "urai": "தோழி! செவ்வியை யுடைய தேனை விரும்பி பல வண்டுக்கூட்டங்கள் உலாவுதலையுடைய அலைகள் மோதிய செறிந்தமணல் அடைந்த கரையின் கண் உள்ள அலைத் துவலையால் நனைந்த புன்னை மரத்தினது பெரிய கிளையின்கண் கூடுகின்ற மலர்ந்த மலர்களையும் கரிய நீரையுமுடைய கடற்கரைத் தலைவன் பொருட்டு வருந்தேன்; இவ்விடத்து இவள் ஏன் இங்ஙனம் ஆயினளென்று பிறர் பிறர் அறியும்படி கூறிதல் அவர்களுடைய மனம் அமைந்தபடி அமைக; அவர்கள் கூறும் அம்பல் என்ன துன்பத்தைச் செய்வதாகும்?",
  "english": null,
  "lines": [
    {
      "lineNumber": 1,
      "text": "பருவத் தேன் நசைஇப் பல் பறைத் தொழுதி,",
      "words": [
        {
          "form": "பருவத்",
          "root": null,
          "urichol": null,
          "etymology": null,
          "gloss": null
        },
        {
          "form": "தேன்",
          "root": null,
          "urichol": null,
          "etymology": null,
          "gloss": null
        },
        {
          "form": "நசைஇப்",
          "root": null,
          "urichol": null,
          "etymology": null,
          "gloss": null
        },
        {
          "form": "பல்",
          "root": null,
          "urichol": null,
          "etymology": null,
          "gloss": null
        },
        {
          "form": "பறைத்",
          "root": null,
          "urichol": null,
          "etymology": null,
          "gloss": null
        },
        {
          "form": "தொழுதி,",
          "root": null,
          "urichol": null,
          "etymology": null,
          "gloss": null
        }
      ]
    },
    {
      "lineNumber": 2,
      "text": "உரவுத் திரை பொருத திணிமணல் அடைகரை,",
      "words": [
        {
          "form": "உரவுத்",
          "root": null,
          "urichol": null,
          "etymology": null,
          "gloss": null
        },
        {
          "form": "திரை",
          "root": null,
          "urichol": null,
          "etymology": null,
          "gloss": null
        },
        {
          "form": "பொருத",
          "root": null,
          "urichol": null,
          "etymology": null,
          "gloss": null
        },
        {
          "form": "திணிமணல்",
          "root": null,
          "urichol": null,
          "etymology": null,
          "gloss": null
        },
        {
          "form": "அடைகரை,",
          "root": null,
          "urichol": null,
          "etymology": null,
          "gloss": null
        }
      ]
    },
    {
      "lineNumber": 3,
      "text": "நனைந்த புன்னை மாச் சினை தொகூஉம்",
      "words": [
        {
          "form": "நனைந்த",
          "root": null,
          "urichol": null,
          "etymology": null,
          "gloss": null
        },
        {
          "form": "புன்னை",
          "root": null,
          "urichol": null,
          "etymology": null,
          "gloss": null
        },
        {
          "form": "மாச்",
          "root": null,
          "urichol": null,
          "etymology": null,
          "gloss": null
        },
        {
          "form": "சினை",
          "root": null,
          "urichol": null,
          "etymology": null,
          "gloss": null
        },
        {
          "form": "தொகூஉம்",
          "root": null,
          "urichol": null,
          "etymology": null,
          "gloss": null
        }
      ]
    },
    {
      "lineNumber": 4,
      "text": "மலர்ந்த பூவின் மா நீர்ச் சேர்ப்பற்கு",
      "words": [
        {
          "form": "மலர்ந்த",
          "root": null,
          "urichol": null,
          "etymology": null,
          "gloss": null
        },
        {
          "form": "பூவின்",
          "root": null,
          "urichol": null,
          "etymology": null,
          "gloss": null
        },
        {
          "form": "மா",
          "root": null,
          "urichol": null,
          "etymology": null,
          "gloss": null
        },
        {
          "form": "நீர்ச்",
          "root": null,
          "urichol": null,
          "etymology": null,
          "gloss": null
        },
        {
          "form": "சேர்ப்பற்கு",
          "root": null,
          "urichol": null,
          "etymology": null,
          "gloss": null
        }
      ]
    },
    {
      "lineNumber": 5,
      "text": "இரங்கேன் - தோழி! - 'ஈங்கு என் கொல்?' என்று",
      "words": [
        {
          "form": "இரங்கேன்",
          "root": null,
          "urichol": null,
          "etymology": null,
          "gloss": null
        },
        {
          "form": "-",
          "root": null,
          "urichol": null,
          "etymology": null,
          "gloss": null
        },
        {
          "form": "தோழி!",
          "root": null,
          "urichol": null,
          "etymology": null,
          "gloss": null
        },
        {
          "form": "-",
          "root": null,
          "urichol": null,
          "etymology": null,
          "gloss": null
        },
        {
          "form": "'ஈங்கு",
          "root": null,
          "urichol": null,
          "etymology": null,
          "gloss": null
        },
        {
          "form": "என்",
          "root": null,
          "urichol": null,
          "etymology": null,
          "gloss": null
        },
        {
          "form": "கொல்?'",
          "root": null,
          "urichol": null,
          "etymology": null,
          "gloss": null
        },
        {
          "form": "என்று",
          "root": null,
          "urichol": null,
          "etymology": null,
          "gloss": null
        }
      ]
    },
    {
      "lineNumber": 6,
      "text": "பிறர்பிறர் அறியக் கூறல்",
      "words": [
        {
          "form": "பிறர்பிறர்",
          "root": null,
          "urichol": null,
          "etymology": null,
          "gloss": null
        },
        {
          "form": "அறியக்",
          "root": null,
          "urichol": null,
          "etymology": null,
          "gloss": null
        },
        {
          "form": "கூறல்",
          "root": null,
          "urichol": null,
          "etymology": null,
          "gloss": null
        }
      ]
    },
    {
      "lineNumber": 7,
      "text": "அமைந்தாங்கு அமைக; அம்பல் அஃது எவனே?",
      "words": [
        {
          "form": "அமைந்தாங்கு",
          "root": null,
          "urichol": null,
          "etymology": null,
          "gloss": null
        },
        {
          "form": "அமைக;",
          "root": null,
          "urichol": null,
          "etymology": null,
          "gloss": null
        },
        {
          "form": "அம்பல்",
          "root": null,
          "urichol": null,
          "etymology": null,
          "gloss": null
        },
        {
          "form": "அஃது",
          "root": null,
          "urichol": null,
          "etymology": null,
          "gloss": null
        },
        {
          "form": "எவனே?",
          "root": null,
          "urichol": null,
          "etymology": null,
          "gloss": null
        }
      ]
    },
    {
      "lineNumber": 8,
      "text": "- உலோச்சனார்.",
      "words": [
        {
          "form": "-",
          "root": null,
          "urichol": null,
          "etymology": null,
          "gloss": null
        },
        {
          "form": "உலோச்சனார்.",
          "root": null,
          "urichol": null,
          "etymology": null,
          "gloss": null
        }
      ]
    }
  ],
  "culturalNotes": [],
  "audioUrl": null,
  "source": "http://www.sangathamizh.com/8thokai/kurunthokai/kurunthokai-குறுந்தொகை175.html",
  "verified": false,
  "number": 175,
  "poet": "உலோச்சனார்."
}