{
  "id": "purananooru_076",
  "poem": "purananooru",
  "tinai": "unknown",
  "sangamTamil": "ஒருவனை ஒருவன் அடுதலும், தொலைதலும்,\nபுதுவது அன்று; இவ் உலகத்து இயற்கை;\nஇன்றின் ஊங்கோ கேளலம்; திரளரை\nமன்ற வேம்பின் மாச்சினை ஒண்தளிர்\nநெடுங்கொடி உழிஞைப் பவரொடு மிடைந்து,\nசெறியத் தொடுத்த தேம்பாய் கண்ணி,\nஒலியல் மாலையடு, பொலியச் சூடிப்,\nபாடின் தெண்கிணை கறங்கக், காண்தக,\nநாடுகெழு திருவிற் பசும்பூட் செழியன்\nபீடும் செம்மலும் அறியார் கூடிப்,\nபொருதும் என்று தன்தலை வந்த\nபுனைகழல் எழுவர் நல்வலம் அடங்க,\nஒருதான் ஆகிப் பொருது, களத்து அடலே!",
  "urai": "தலையாலங்கானப் போரில் பாண்டியன் நெடுஞ்செழியன் ஏழு அரசர்களை எதிர்த்துப் போரிட்டதைக் கண்ட புலவர் இவ்வாறு பாடுகிறார். ஒருவனை ஒருவன் தாக்கிப் போரிடுவதும், அப்போது ஒருவனோ அல்லது இருவருமோ மாண்டுபோவதும் இயல்புதான். ஆனால் ஒருவன் ஏழு பேரைத் தாக்கி அழித்தல் புதுமையானது. அதனை இன்று கண்டோம். இதற்கு முன்பு கண்டதில்லை. பசும்பூண் செழியனின் பெருமையையும் செம்மாப்பையும் அறியாமல் அவனை எதிர்த்துப் போரிடுவோம் என வந்த எழுவரின் கொட்டம் அடங்க வேப்பம்பூவும், உழிஞையும் சேர்த்துத் தலையில் சூடிக்கொண்டு, கிணைப்பறை முழக்கத்துடன் போரிட்டு அழித்தலை இன்றுதான் காண்கிறேன்.",
  "english": null,
  "lines": [
    {
      "lineNumber": 1,
      "text": "ஒருவனை ஒருவன் அடுதலும், தொலைதலும்,",
      "words": [
        {
          "form": "ஒருவனை",
          "root": null,
          "urichol": null,
          "etymology": null,
          "gloss": null
        },
        {
          "form": "ஒருவன்",
          "root": null,
          "urichol": null,
          "etymology": null,
          "gloss": null
        },
        {
          "form": "அடுதலும்,",
          "root": null,
          "urichol": null,
          "etymology": null,
          "gloss": null
        },
        {
          "form": "தொலைதலும்,",
          "root": null,
          "urichol": null,
          "etymology": null,
          "gloss": null
        }
      ]
    },
    {
      "lineNumber": 2,
      "text": "புதுவது அன்று; இவ் உலகத்து இயற்கை;",
      "words": [
        {
          "form": "புதுவது",
          "root": null,
          "urichol": null,
          "etymology": null,
          "gloss": null
        },
        {
          "form": "அன்று;",
          "root": null,
          "urichol": null,
          "etymology": null,
          "gloss": null
        },
        {
          "form": "இவ்",
          "root": null,
          "urichol": null,
          "etymology": null,
          "gloss": null
        },
        {
          "form": "உலகத்து",
          "root": null,
          "urichol": null,
          "etymology": null,
          "gloss": null
        },
        {
          "form": "இயற்கை;",
          "root": null,
          "urichol": null,
          "etymology": null,
          "gloss": null
        }
      ]
    },
    {
      "lineNumber": 3,
      "text": "இன்றின் ஊங்கோ கேளலம்; திரளரை",
      "words": [
        {
          "form": "இன்றின்",
          "root": null,
          "urichol": null,
          "etymology": null,
          "gloss": null
        },
        {
          "form": "ஊங்கோ",
          "root": null,
          "urichol": null,
          "etymology": null,
          "gloss": null
        },
        {
          "form": "கேளலம்;",
          "root": null,
          "urichol": null,
          "etymology": null,
          "gloss": null
        },
        {
          "form": "திரளரை",
          "root": null,
          "urichol": null,
          "etymology": null,
          "gloss": null
        }
      ]
    },
    {
      "lineNumber": 4,
      "text": "மன்ற வேம்பின் மாச்சினை ஒண்தளிர்",
      "words": [
        {
          "form": "மன்ற",
          "root": null,
          "urichol": null,
          "etymology": null,
          "gloss": null
        },
        {
          "form": "வேம்பின்",
          "root": null,
          "urichol": null,
          "etymology": null,
          "gloss": null
        },
        {
          "form": "மாச்சினை",
          "root": null,
          "urichol": null,
          "etymology": null,
          "gloss": null
        },
        {
          "form": "ஒண்தளிர்",
          "root": null,
          "urichol": null,
          "etymology": null,
          "gloss": null
        }
      ]
    },
    {
      "lineNumber": 5,
      "text": "நெடுங்கொடி உழிஞைப் பவரொடு மிடைந்து,",
      "words": [
        {
          "form": "நெடுங்கொடி",
          "root": null,
          "urichol": null,
          "etymology": null,
          "gloss": null
        },
        {
          "form": "உழிஞைப்",
          "root": null,
          "urichol": null,
          "etymology": null,
          "gloss": null
        },
        {
          "form": "பவரொடு",
          "root": null,
          "urichol": null,
          "etymology": null,
          "gloss": null
        },
        {
          "form": "மிடைந்து,",
          "root": null,
          "urichol": null,
          "etymology": null,
          "gloss": null
        }
      ]
    },
    {
      "lineNumber": 6,
      "text": "செறியத் தொடுத்த தேம்பாய் கண்ணி,",
      "words": [
        {
          "form": "செறியத்",
          "root": null,
          "urichol": null,
          "etymology": null,
          "gloss": null
        },
        {
          "form": "தொடுத்த",
          "root": null,
          "urichol": null,
          "etymology": null,
          "gloss": null
        },
        {
          "form": "தேம்பாய்",
          "root": null,
          "urichol": null,
          "etymology": null,
          "gloss": null
        },
        {
          "form": "கண்ணி,",
          "root": null,
          "urichol": null,
          "etymology": null,
          "gloss": null
        }
      ]
    },
    {
      "lineNumber": 7,
      "text": "ஒலியல் மாலையடு, பொலியச் சூடிப்,",
      "words": [
        {
          "form": "ஒலியல்",
          "root": null,
          "urichol": null,
          "etymology": null,
          "gloss": null
        },
        {
          "form": "மாலையடு,",
          "root": null,
          "urichol": null,
          "etymology": null,
          "gloss": null
        },
        {
          "form": "பொலியச்",
          "root": null,
          "urichol": null,
          "etymology": null,
          "gloss": null
        },
        {
          "form": "சூடிப்,",
          "root": null,
          "urichol": null,
          "etymology": null,
          "gloss": null
        }
      ]
    },
    {
      "lineNumber": 8,
      "text": "பாடின் தெண்கிணை கறங்கக், காண்தக,",
      "words": [
        {
          "form": "பாடின்",
          "root": null,
          "urichol": null,
          "etymology": null,
          "gloss": null
        },
        {
          "form": "தெண்கிணை",
          "root": null,
          "urichol": null,
          "etymology": null,
          "gloss": null
        },
        {
          "form": "கறங்கக்,",
          "root": null,
          "urichol": null,
          "etymology": null,
          "gloss": null
        },
        {
          "form": "காண்தக,",
          "root": null,
          "urichol": null,
          "etymology": null,
          "gloss": null
        }
      ]
    },
    {
      "lineNumber": 9,
      "text": "நாடுகெழு திருவிற் பசும்பூட் செழியன்",
      "words": [
        {
          "form": "நாடுகெழு",
          "root": null,
          "urichol": null,
          "etymology": null,
          "gloss": null
        },
        {
          "form": "திருவிற்",
          "root": null,
          "urichol": null,
          "etymology": null,
          "gloss": null
        },
        {
          "form": "பசும்பூட்",
          "root": null,
          "urichol": null,
          "etymology": null,
          "gloss": null
        },
        {
          "form": "செழியன்",
          "root": null,
          "urichol": null,
          "etymology": null,
          "gloss": null
        }
      ]
    },
    {
      "lineNumber": 10,
      "text": "பீடும் செம்மலும் அறியார் கூடிப்,",
      "words": [
        {
          "form": "பீடும்",
          "root": null,
          "urichol": null,
          "etymology": null,
          "gloss": null
        },
        {
          "form": "செம்மலும்",
          "root": null,
          "urichol": null,
          "etymology": null,
          "gloss": null
        },
        {
          "form": "அறியார்",
          "root": null,
          "urichol": null,
          "etymology": null,
          "gloss": null
        },
        {
          "form": "கூடிப்,",
          "root": null,
          "urichol": null,
          "etymology": null,
          "gloss": null
        }
      ]
    },
    {
      "lineNumber": 11,
      "text": "பொருதும் என்று தன்தலை வந்த",
      "words": [
        {
          "form": "பொருதும்",
          "root": null,
          "urichol": null,
          "etymology": null,
          "gloss": null
        },
        {
          "form": "என்று",
          "root": null,
          "urichol": null,
          "etymology": null,
          "gloss": null
        },
        {
          "form": "தன்தலை",
          "root": null,
          "urichol": null,
          "etymology": null,
          "gloss": null
        },
        {
          "form": "வந்த",
          "root": null,
          "urichol": null,
          "etymology": null,
          "gloss": null
        }
      ]
    },
    {
      "lineNumber": 12,
      "text": "புனைகழல் எழுவர் நல்வலம் அடங்க,",
      "words": [
        {
          "form": "புனைகழல்",
          "root": null,
          "urichol": null,
          "etymology": null,
          "gloss": null
        },
        {
          "form": "எழுவர்",
          "root": null,
          "urichol": null,
          "etymology": null,
          "gloss": null
        },
        {
          "form": "நல்வலம்",
          "root": null,
          "urichol": null,
          "etymology": null,
          "gloss": null
        },
        {
          "form": "அடங்க,",
          "root": null,
          "urichol": null,
          "etymology": null,
          "gloss": null
        }
      ]
    },
    {
      "lineNumber": 13,
      "text": "ஒருதான் ஆகிப் பொருது, களத்து அடலே!",
      "words": [
        {
          "form": "ஒருதான்",
          "root": null,
          "urichol": null,
          "etymology": null,
          "gloss": null
        },
        {
          "form": "ஆகிப்",
          "root": null,
          "urichol": null,
          "etymology": null,
          "gloss": null
        },
        {
          "form": "பொருது,",
          "root": null,
          "urichol": null,
          "etymology": null,
          "gloss": null
        },
        {
          "form": "களத்து",
          "root": null,
          "urichol": null,
          "etymology": null,
          "gloss": null
        },
        {
          "form": "அடலே!",
          "root": null,
          "urichol": null,
          "etymology": null,
          "gloss": null
        }
      ]
    }
  ],
  "culturalNotes": [],
  "audioUrl": null,
  "source": "http://www.sangathamizh.com/8thokai/purananooru/purananooru-புறநானூறு076.html",
  "verified": false,
  "number": 76,
  "poet": null
}